{
  "vendors": {
    "Shopping": [
      "Amazon",
      "Walmart",
      "Target",
      "Best Buy",
      "Macy's",
      "Costco",
      "Home Depot",
      "Lowe's",
      "IKEA",
      "Wayfair",
      "Overstock",
      "Nordstrom",
      "JCPenney",
      "Sears",
      "Kohl's",
      "TJ Maxx",
      "Marshalls",
      "Bed Bath & Beyond",
      "Sam's Club",
      "Dollar Tree",
      "Dollar General",
      "Five Below",
      "Big Lots",
      "Barnes & Noble",
      "Apple Store",
      "Microsoft Store",
      "Staples",
      "Office Depot",
      "PetSmart",
      "Petco"
    ],
    "Groceries": [
      "Whole Foods",
      "Trader Joe's",
      "Kroger",
      "Aldi",
      "Safeway",
      "Publix",
      "Wegmans",
      "Sprouts Farmers Market",
      "Albertsons",
      "H-E-B",
      "Hy-Vee",
      "Meijer",
      "Food Lion",
      "Giant Eagle",
      "Stop & Shop",
      "Hannaford",
      "WinCo Foods",
      "ShopRite",
      "Fresh Market",
      "Harris Teeter",
      "Piggly Wiggly",
      "Save-A-Lot"
    ],
    "Utilities": [
      "Comcast",
      "Verizon",
      "AT&T",
      "Duke Energy",
      "Pacific Gas and Electric",
      "National Grid",
      "Con Edison",
      "Xcel Energy",
      "Southern California Edison",
      "Florida Power & Light",
      "Dominion Energy",
      "American Electric Power",
      "Entergy",
      "FirstEnergy",
      "PPL Electric Utilities",
      "CenterPoint Energy",
      "Exelon",
      "Consumers Energy",
      "NRG Energy"
    ],
    "Health": [
      "CVS Pharmacy",
      "Walgreens",
      "Rite Aid",
      "Kaiser Permanente",
      "UnitedHealthcare",
      "Anthem",
      "Cigna",
      "Blue Cross Blue Shield",
      "Humana",
      "Aetna",
      "Molina Healthcare",
      "WellCare",
      "Centene",
      "Magellan Health",
      "CVS Health"
    ],
    "Transportation": [
      "Uber",
      "Lyft",
      "Delta Airlines",
      "American Airlines",
      "United Airlines",
      "Southwest Airlines",
      "Greyhound",
      "Amtrak",
      "JetBlue",
      "Alaska Airlines",
      "Spirit Airlines",
      "Frontier Airlines",
      "Enterprise Rent-A-Car",
      "Hertz",
      "Avis",
      "Budget",
      "National Car Rental",
      "Thrifty Car Rental",
      "Dollar Rent A Car"
    ],
    "Education": [
      "Coursera",
      "Udemy",
      "edX",
      "Khan Academy",
      "LinkedIn Learning",
      "Skillshare",
      "MasterClass",
      "FutureLearn",
      "Udacity",
      "Codecademy",
      "Pluralsight",
      "Lynda.com",
      "Treehouse",
      "Duolingo",
      "Rosetta Stone"
    ],
    "Entertainment": [
      "Netflix",
      "Hulu",
      "Spotify",
      "Disney+",
      "HBO Max",
      "Amazon Prime Video",
      "Apple Music",
      "YouTube Premium",
      "Pandora",
      "Tidal",
      "SiriusXM",
      "Peacock",
      "Paramount+",
      "Showtime",
      "Crunchyroll",
      "Funimation",
      "Deezer",
      "Audible"
    ],
    "Insurance": [
      "Geico",
      "State Farm",
      "Progressive",
      "Allstate",
      "Liberty Mutual",
      "Nationwide",
      "USAA",
      "Farmers Insurance",
      "Travelers",
      "American Family Insurance",
      "Chubb",
      "MetLife",
      "AIG",
      "Hartford",
      "Erie Insurance",
      "Amica",
      "Safeco",
      "Auto-Owners Insurance"
    ],
    "Dining": [
      "McDonald's",
      "Starbucks",
      "Subway",
      "Pizza Hut",
      "Taco Bell",
      "Burger King",
      "Dunkin'",
      "Chipotle",
      "Panera Bread",
      "KFC",
      "Panda Express",
      "Olive Garden",
      "Red Lobster",
      "Chili's",
      "Outback Steakhouse",
      "Buffalo Wild Wings",
      "Applebee's",
      "IHOP",
      "Denny's",
      "Wendy's",
      "Jack in the Box",
      "Arby's",
      "Five Guys",
      "Shake Shack",
      "Sonic Drive-In"
    ]
  }
}
